anydyce/__init__.py
anydyce/_version.py
anydyce/py.typed
anydyce/viz.py
anydyce-0.4.6.dist-info/LICENSE
anydyce-0.4.6.dist-info/METADATA
anydyce-0.4.6.dist-info/WHEEL
anydyce-0.4.6.dist-info/top_level.txt
anydyce-0.4.6.dist-info/RECORD
