Metadata-Version: 2.1
Name: anydyce
Version: 0.4.6
Summary: Visualization tools for dyce
Home-page: https://posita.github.io/anydyce/
Author: Matt Bogosian
Author-email: matt@bogosian.net
License: MIT License
Project-URL: Source Repository, https://github.com/posita/anydyce/
Classifier: Topic :: Education
Classifier: Topic :: Games/Entertainment
Classifier: Topic :: Scientific/Engineering :: Mathematics
Classifier: Topic :: Software Development :: Libraries :: Python Modules
Classifier: Typing :: Typed
Classifier: Development Status :: 3 - Alpha
Classifier: Intended Audience :: Developers
Classifier: Intended Audience :: Education
Classifier: Intended Audience :: Science/Research
Classifier: License :: OSI Approved :: MIT License
Classifier: Operating System :: OS Independent
Classifier: Programming Language :: Python
Classifier: Programming Language :: Python :: 3.9
Classifier: Programming Language :: Python :: 3.10
Classifier: Programming Language :: Python :: 3.11
Classifier: Programming Language :: Python :: Implementation :: CPython
Requires-Python: >=3.9
License-File: LICENSE
Requires-Dist: dyce~=0.6.0
Requires-Dist: ipywidgets<9,>=7.5
Requires-Dist: matplotlib<4,~=3.5
Provides-Extra: dev
Requires-Dist: pre-commit; extra == "dev"
Requires-Dist: tox~=4.0; extra == "dev"
Requires-Dist: versioningit~=2.0; extra == "dev"
